macchiato.py
black_macchiato-1.3.0.dist-info/LICENSE.rst
black_macchiato-1.3.0.dist-info/METADATA
black_macchiato-1.3.0.dist-info/WHEEL
black_macchiato-1.3.0.dist-info/entry_points.txt
black_macchiato-1.3.0.dist-info/top_level.txt
black_macchiato-1.3.0.dist-info/RECORD
