Metadata-Version: 2.1
Name: black-macchiato
Version: 1.3.0
Summary: Partial black formatting
Home-page: https://github.com/wbolster/black-macchiato
Author: wouter bolsterlee
Author-email: wouter@bolsterl.ee
License: BSD License
Platform: UNKNOWN
Classifier: Development Status :: 5 - Production/Stable
Classifier: Intended Audience :: Developers
Classifier: License :: OSI Approved :: BSD License
Classifier: Programming Language :: Python
Classifier: Programming Language :: Python :: 2
Classifier: Programming Language :: Python :: 3
Requires-Python: >=3.6
Requires-Dist: black
